README.md
setup.cfg
setup.py
TOPSIS_ParthArora_101853039/Topsis.py
TOPSIS_ParthArora_101853039.egg-info/PKG-INFO
TOPSIS_ParthArora_101853039.egg-info/SOURCES.txt
TOPSIS_ParthArora_101853039.egg-info/dependency_links.txt
TOPSIS_ParthArora_101853039.egg-info/entry_points.txt
TOPSIS_ParthArora_101853039.egg-info/requires.txt
TOPSIS_ParthArora_101853039.egg-info/top_level.txt