Metadata-Version: 2.1
Name: TOPSIS-ParthArora-101853039
Version: 1.0
Summary: This Package is for calculating the TOPSIS score and rank of a dataset and storing it in a result csv file
Home-page: https://github.com/parthrr510/TOPSIS-ParthArora-101853039.git
Author: parthrr510
Author-email: parthrr510@gmail.com
License: MIT
Download-URL: https://github.com/parthrr510/TOPSIS-ParthArora-101853039/archive/v_02.tar.gz
Keywords: TOPSIS,RANKING,DATAFRAME,MCDM
Platform: UNKNOWN
Classifier: Development Status :: 3 - Alpha
Classifier: Intended Audience :: Developers
Classifier: Topic :: Software Development :: Build Tools
Classifier: License :: OSI Approved :: MIT License
Classifier: Programming Language :: Python :: 3
Classifier: Programming Language :: Python :: 3.4
Classifier: Programming Language :: Python :: 3.5
Classifier: Programming Language :: Python :: 3.6
Classifier: Programming Language :: Python :: 3.7
Classifier: Programming Language :: Python :: 3.8
